{
  "current_workspace": null,
  "recent_workflows": [
    "gaming",
    "work",
    "work",
    "work",
    "gaming",
    "gaming",
    "test",
    "work",
    "work",
    "work",
    "work",
    "work",
    "python-setup",
    "python-setup",
    "work",
    "work"
  ],
  "recent_commands": [
    "pwd",
    "cd ..",
    "pwd",
    "cls",
    "music",
    "help",
    "cls",
    "mode",
    "norm",
    "cls",
    "music",
    "music The",
    "music",
    "music blinding_lights",
    "music pause",
    "cls",
    "music",
    "music blinding_lights",
    "music pause",
    "cls"
  ],
  "theme": "glacier",
  "quote_index": 130,
  "converter_mode": "pdf_to_doc",
  "norm_mode": false
}